README.md
setup.py
sunnyday/__init__.py
sunnyday/sunnyday.py
sunnyday_fff.egg-info/PKG-INFO
sunnyday_fff.egg-info/SOURCES.txt
sunnyday_fff.egg-info/dependency_links.txt
sunnyday_fff.egg-info/requires.txt
sunnyday_fff.egg-info/top_level.txt