Metadata-Version: 2.1
Name: sunnyday-fff
Version: 1.0.0
Summary: Weather forecast data
Home-page: https://github.com/FrostFireFalcon
Author: FrostFireFalcon
Author-email: i.simac.8@gmail.com
License: MIT
Keywords: weather,forecast,openweather
Classifier: Development Status :: 4 - Beta
Classifier: Intended Audience :: Developers
Classifier: Topic :: Software Development :: Build Tools
Classifier: License :: OSI Approved :: MIT License
Classifier: Programming Language :: Python :: 3.10
